airflow_provider_azure_machinelearning/__init__.py
airflow_provider_azure_machinelearning/example_dags/AML_2Subs.py
airflow_provider_azure_machinelearning/example_dags/AML_AutoML.py
airflow_provider_azure_machinelearning/example_dags/AML_CommandJob.py
airflow_provider_azure_machinelearning/example_dags/AML_Component.py
airflow_provider_azure_machinelearning/example_dags/AML_Compute.py
airflow_provider_azure_machinelearning/example_dags/AML_Endpoint.py
airflow_provider_azure_machinelearning/example_dags/AML_Environment.py
airflow_provider_azure_machinelearning/example_dags/AML_ParallelJob.py
airflow_provider_azure_machinelearning/example_dags/AML_Pipeline.py
airflow_provider_azure_machinelearning/example_dags/AML_PyEnv.py
airflow_provider_azure_machinelearning/example_dags/AML_SweepJob.py
airflow_provider_azure_machinelearning/example_dags/AML_data.py
airflow_provider_azure_machinelearning/example_dags/__init__.py
airflow_provider_azure_machinelearning/hooks/__init__.py
airflow_provider_azure_machinelearning/hooks/machine_learning.py
airflow_provider_azure_machinelearning/operators/__init__.py
airflow_provider_azure_machinelearning/operators/machine_learning/__init__.py
airflow_provider_azure_machinelearning/operators/machine_learning/component.py
airflow_provider_azure_machinelearning/operators/machine_learning/compute.py
airflow_provider_azure_machinelearning/operators/machine_learning/data.py
airflow_provider_azure_machinelearning/operators/machine_learning/endpoint.py
airflow_provider_azure_machinelearning/operators/machine_learning/environment.py
airflow_provider_azure_machinelearning/operators/machine_learning/job.py
airflow_provider_azure_machinelearning/operators/machine_learning/model.py
tests/__init__.py
airflow_provider_azure_machinelearning-0.0.1b2.dist-info/LICENSE
airflow_provider_azure_machinelearning-0.0.1b2.dist-info/METADATA
airflow_provider_azure_machinelearning-0.0.1b2.dist-info/WHEEL
airflow_provider_azure_machinelearning-0.0.1b2.dist-info/entry_points.txt
airflow_provider_azure_machinelearning-0.0.1b2.dist-info/top_level.txt
airflow_provider_azure_machinelearning-0.0.1b2.dist-info/RECORD
