Metadata-Version: 2.1
Name: airflow-provider-azure-machinelearning
Version: 0.0.1b2
Summary: Airflow provider package for Azure Machine Learning
Home-page: https://github.com/Azure/airflow-provider-azure-machinelearning/
Author: Microsoft Corporation
Author-email: amlairflowsupport@microsoft.com
License: MIT License
Project-URL: Bug Tracker, https://github.com/Azure/airflow-provider-azure-machinelearning/issues
Classifier: Development Status :: 4 - Beta
Classifier: Framework :: Apache Airflow
Classifier: Framework :: Apache Airflow :: Provider
Classifier: License :: OSI Approved :: MIT License
Classifier: Programming Language :: Python
Classifier: Programming Language :: Python :: 3.7
Classifier: Programming Language :: Python :: 3.8
Classifier: Programming Language :: Python :: 3.9
Classifier: Programming Language :: Python :: 3.10
Requires-Python: >=3.7
License-File: LICENSE
Requires-Dist: apache-airflow (>=2.0)
Requires-Dist: azure-ai-ml (>=1.0.0")
